pyoscar/__init__.py
pyoscar/cli_options.py
pyoscar-0.9.0.dist-info/LICENSE
pyoscar-0.9.0.dist-info/METADATA
pyoscar-0.9.0.dist-info/WHEEL
pyoscar-0.9.0.dist-info/entry_points.txt
pyoscar-0.9.0.dist-info/top_level.txt
pyoscar-0.9.0.dist-info/RECORD
