Metadata-Version: 2.1
Name: pyoscar
Version: 0.9.0
Summary: Pythonic API to WMO OSCAR Web Services
Home-page: https://github.com/wmo-cop/pyoscar
Author: Meteorological Service of Canada
Author-email: tomkralidis@gmail.com
Maintainer: Meteorological Service of Canada
Maintainer-email: tomkralidis@gmail.com
License: MIT
Keywords: wmo oscar wigos station metadata gawsis
Platform: all
Classifier: Development Status :: 4 - Beta
Classifier: Environment :: Console
Classifier: Intended Audience :: Developers
Classifier: Intended Audience :: Science/Research
Classifier: License :: OSI Approved :: MIT License
Classifier: Operating System :: OS Independent
Classifier: Programming Language :: Python
Classifier: Topic :: Scientific/Engineering :: GIS
License-File: LICENSE
Requires-Dist: beautifulsoup4
Requires-Dist: click
Requires-Dist: lxml
Requires-Dist: requests
